loxodonta/__init__.py
loxodonta/cli.py
loxodonta/config.py
loxodonta/logger.py
loxodonta/analyzer/__init__.py
loxodonta/analyzer/analyzer.py
loxodonta/analyzer/fact.py
loxodonta/analyzer/protocol.py
loxodonta/analyzer/application/__init__.py
loxodonta/analyzer/application/dns.py
loxodonta/analyzer/application/http.py
loxodonta/analyzer/application/ref.py
loxodonta/analyzer/application/smb.py
loxodonta/analyzer/application/ssh.py
loxodonta/analyzer/data_link/__init__.py
loxodonta/analyzer/data_link/arp.py
loxodonta/analyzer/data_link/ethernet.py
loxodonta/analyzer/data_link/ref.py
loxodonta/analyzer/network/__init__.py
loxodonta/analyzer/network/ip.py
loxodonta/analyzer/network/ref.py
loxodonta/analyzer/transport/__init__.py
loxodonta/analyzer/transport/ref.py
loxodonta/analyzer/transport/tcp.py
loxodonta/analyzer/transport/udp.py
loxodonta/data_loader/__init__.py
loxodonta/data_loader/loader.py
loxodonta-0.1.1.dist-info/METADATA
loxodonta-0.1.1.dist-info/WHEEL
loxodonta-0.1.1.dist-info/entry_points.txt
loxodonta-0.1.1.dist-info/top_level.txt
loxodonta-0.1.1.dist-info/RECORD
